odoo8_addon_project_construction_site-8.0.0.1.0-py2.7-nspkg.pth
odoo_addons/project_construction_site/views.xml
odoo_addons/project_construction_site/models.py
odoo_addons/project_construction_site/__openerp__.py
odoo_addons/project_construction_site/__init__.py
odoo_addons/project_construction_site/README.rst
odoo_addons/project_construction_site/i18n/project_construction_site.po
odoo_addons/project_construction_site/i18n/nl_BE.po
odoo_addons/project_construction_site/tests/__init__.py
odoo_addons/project_construction_site/tests/test_onchange_partner_id.py
odoo_addons/project_construction_site/static/description/index.html
odoo_addons/project_construction_site/static/description/icon.png
odoo8_addon_project_construction_site-8.0.0.1.0.dist-info/top_level.txt
odoo8_addon_project_construction_site-8.0.0.1.0.dist-info/WHEEL
odoo8_addon_project_construction_site-8.0.0.1.0.dist-info/RECORD
odoo8_addon_project_construction_site-8.0.0.1.0.dist-info/metadata.json
odoo8_addon_project_construction_site-8.0.0.1.0.dist-info/DESCRIPTION.rst
odoo8_addon_project_construction_site-8.0.0.1.0.dist-info/METADATA
odoo8_addon_project_construction_site-8.0.0.1.0.dist-info/namespace_packages.txt
